qnty/__init__.py
qnty/algebra/__init__.py
qnty/algebra/equation.py
qnty/algebra/formatter.py
qnty/algebra/functions.py
qnty/algebra/nodes.py
qnty/algebra/select.py
qnty/algebra/system.py
qnty/constants/__init__.py
qnty/constants/numerical.py
qnty/constants/solvers.py
qnty/constants/tests.py
qnty/core/CLAUDE.md
qnty/core/__init__.py
qnty/core/dimension.py
qnty/core/dimension_catalog.py
qnty/core/dimension_catalog.pyi
qnty/core/quantity.py
qnty/core/quantity_catalog.py
qnty/core/quantity_catalog.pyi
qnty/core/quantity_meta.py
qnty/core/unit.py
qnty/core/unit_catalog.py
qnty/core/unit_catalog.pyi
qnty/core/units/length.json
qnty/extensions/__init__.py
qnty/extensions/integration/__init__.py
qnty/extensions/plotting/__init__.py
qnty/extensions/plotting/vector_diagram.py
qnty/extensions/reporting/__init__.py
qnty/extensions/reporting/base.py
qnty/extensions/reporting/formats.py
qnty/extensions/reporting/generator.py
qnty/extensions/reporting/reports/pipe_thickness_output_units.md
qnty/extensions/reporting/reports/pipe_thickness_output_units.pdf
qnty/extensions/reporting/reports/pipe_thickness_output_units.tex
qnty/extensions/reporting/tectonic
qnty/extensions/reporting/tectonic.exe
qnty/extensions/reporting/vector_diagram.py
qnty/problems/__init__.py
qnty/problems/composition.py
qnty/problems/problem.py
qnty/problems/rules.py
qnty/problems/solving.py
qnty/problems/validation.py
qnty/problems/vector_equilibrium.py
qnty/solving/__init__.py
qnty/solving/manager.py
qnty/solving/manager.py.bak
qnty/solving/order.py
qnty/solving/solvers/__init__.py
qnty/solving/solvers/base.py
qnty/solving/solvers/iterative.py
qnty/solving/solvers/simultaneous.py
qnty/solving/trig_solver.py
qnty/solving/utils.py
qnty/spatial/__init__.py
qnty/spatial/angle_reference.py
qnty/spatial/coordinate_system.py
qnty/spatial/force_vector.py
qnty/spatial/point.py
qnty/spatial/vector.py
qnty/utils/__init__.py
qnty/utils/caching/__init__.py
qnty/utils/caching/manager.py
qnty/utils/logging.py
qnty-0.3.0.dist-info/METADATA
qnty-0.3.0.dist-info/WHEEL
qnty-0.3.0.dist-info/RECORD
