Metadata-Version: 2.4
Name: qnty
Version: 0.3.0
Summary: High-performance unit system library for Python with dimensional safety and fast unit conversions
License: Apache-2.0
Keywords: units,dimensional analysis,engineering,physics,quantities,measurements
Author: tn3wman
Requires-Python: >=3.11, <3.14
Classifier: Development Status :: 4 - Beta
Classifier: Intended Audience :: Developers
Classifier: Intended Audience :: Science/Research
Classifier: License :: OSI Approved :: Apache Software License
Classifier: Programming Language :: Python :: 3
Classifier: Programming Language :: Python :: 3.11
Classifier: Programming Language :: Python :: 3.12
Classifier: Programming Language :: Python :: 3.13
Classifier: Topic :: Scientific/Engineering
Classifier: Topic :: Scientific/Engineering :: Physics
Classifier: Topic :: Software Development :: Libraries :: Python Modules
Provides-Extra: benchmark
Provides-Extra: dev
Provides-Extra: reporting
Requires-Dist: Pint (>=0.24.4) ; extra == "benchmark"
Requires-Dist: matplotlib (>=3.7.0) ; extra == "reporting"
Requires-Dist: numpy (>=2.3.2)
Requires-Dist: pytest (>=8.4.1) ; extra == "dev"
Requires-Dist: ruff (>=0.1.0) ; extra == "dev"
Project-URL: Bug Tracker, https://github.com/tn3wman/qnty/issues
Project-URL: Documentation, https://github.com/tn3wman/qnty#readme
Project-URL: Homepage, https://github.com/tn3wman/qnty
Project-URL: Repository, https://github.com/tn3wman/qnty
